{"0": {"25967080": {"original": "0-25967080.pt", "structural": null, "contextual": null}, "25967119": {"original": "0-25967119.pt", "structural": null, "contextual": null}, "25967134": {"original": "0-25967134.pt", "structural": null, "contextual": null}, "25967139": {"original": "0-25967139.pt", "structural": null, "contextual": null}}, "2": {"25967064": {"original": "2-25967064.pt", "structural": null, "contextual": null}, "25967065": {"original": "2-25967065.pt", "structural": null, "contextual": null}, "25967127": {"original": "2-25967127.pt", "structural": null, "contextual": null}, "25967130": {"original": "2-25967130.pt", "structural": null, "contextual": null}, "25967132": {"original": "2-25967132.pt", "structural": null, "contextual": null}, "25967133": {"original": "2-25967133.pt", "structural": null, "contextual": null}, "25967138": {"original": "2-25967138.pt", "structural": null, "contextual": null}}, "1": {"25967081": {"original": "1-25967081.pt", "structural": null, "contextual": null}, "25967087": {"original": "1-25967087.pt", "structural": null, "contextual": null}, "25967137": {"original": "1-25967137.pt", "structural": null, "contextual": null}, "25967139": {"original": "1-25967139.pt", "structural": null, "contextual": null}}, "0": {"25967080": {"original": "0-25967080.pt", "structural": null, "contextual": null}, "25967119": {"original": "0-25967119.pt", "structural": null, "contextual": null}, "25967134": {"original": "0-25967134.pt", "structural": null, "contextual": null}, "25967139": {"original": "0-25967139.pt", "structural": null, "contextual": null}}, "2": {"25967064": {"original": "2-25967064.pt", "structural": null, "contextual": null}, "25967065": {"original": "2-25967065.pt", "structural": null, "contextual": null}, "25967127": {"original": "2-25967127.pt", "structural": null, "contextual": null}, "25967130": {"original": "2-25967130.pt", "structural": null, "contextual": null}, "25967132": {"original": "2-25967132.pt", "structural": null, "contextual": null}, "25967133": {"original": "2-25967133.pt", "structural": null, "contextual": null}, "25967138": {"original": "2-25967138.pt", "structural": null, "contextual": null}}, "1": {"25967081": {"original": "1-25967081.pt", "structural": null, "contextual": null}, "25967087": {"original": "1-25967087.pt", "structural": null, "contextual": null}, "25967137": {"original": "1-25967137.pt", "structural": null, "contextual": null}, "25967139": {"original": "1-25967139.pt", "structural": null, "contextual": null}}}